HISTORY.rst
LICENSE.txt
MANIFEST.in
README.rst
linkm
linkmanager.conf
linkmanager.zsh
setup.py
docs/linkm.1.gz
docs/linkmanager.1
docs/linkmanager.1.gz
linkmanager/__init__.py
linkmanager/default.conf
linkmanager/settings.py
linkmanager/translation.py
linkmanager/tty.py
linkmanager/validators.py
linkmanager.egg-info/PKG-INFO
linkmanager.egg-info/SOURCES.txt
linkmanager.egg-info/dependency_links.txt
linkmanager.egg-info/requires.txt
linkmanager.egg-info/top_level.txt
linkmanager.egg-info/zip-safe
linkmanager/db/__init__.py
linkmanager/locale/fr/LC_MESSAGES/linkmanager.mo
linkmanager/locale/fr/LC_MESSAGES/linkmanager.po
linkmanager/tests/__init__.py
linkmanager/tests/db.py
linkmanager/tests/fakesettings.py
linkmanager/tests/interface.py
linkmanager/tests/tests.py
linkmserver/__init__.py
linkmserver/static/favicon.ico
linkmserver/static/favicon.png
linkmserver/static/css/bootstrap.min.css
linkmserver/static/css/jquery-ui.css
linkmserver/static/css/jquery.tagit.css
linkmserver/static/css/normalize.css
linkmserver/static/css/style.css
linkmserver/static/css/images/animated-overlay.gif
linkmserver/static/css/images/ui-bg_diagonals-thick_18_b81900_40x40.png
linkmserver/static/css/images/ui-bg_diagonals-thick_20_666666_40x40.png
linkmserver/static/css/images/ui-bg_flat_10_000000_40x100.png
linkmserver/static/css/images/ui-bg_glass_100_f6f6f6_1x400.png
linkmserver/static/css/images/ui-bg_glass_100_fdf5ce_1x400.png
linkmserver/static/css/images/ui-bg_glass_65_ffffff_1x400.png
linkmserver/static/css/images/ui-bg_gloss-wave_35_f6a828_500x100.png
linkmserver/static/css/images/ui-bg_highlight-soft_100_eeeeee_1x100.png
linkmserver/static/css/images/ui-bg_highlight-soft_75_ffe45c_1x100.png
linkmserver/static/css/images/ui-icons_222222_256x240.png
linkmserver/static/css/images/ui-icons_228ef1_256x240.png
linkmserver/static/css/images/ui-icons_ef8c08_256x240.png
linkmserver/static/css/images/ui-icons_ffd27a_256x240.png
linkmserver/static/css/images/ui-icons_ffffff_256x240.png
linkmserver/static/fonts/glyphicons-halflings-regular.eot
linkmserver/static/fonts/glyphicons-halflings-regular.svg
linkmserver/static/fonts/glyphicons-halflings-regular.ttf
