Metadata-Version: 1.1
Name: linkmanager
Version: 0.4.0.16
Summary: Manage your link on terminal
Home-page: https://github.com/mothsART/linkmanager
Author: Jérémie Ferry
Author-email: jerem.ferry@gmail.com
License: BSD
Keywords: manager link links URL prompt shell
Platform: Linux
Classifier: Development Status :: 4 - Beta
Classifier: Environment :: Console
Classifier: License :: OSI Approved :: BSD License
Classifier: Operating System :: POSIX :: Linux
Classifier: Programming Language :: Python
Classifier: Programming Language :: Python :: 3.3
Classifier: Topic :: Terminals :: Terminal Emulators/X Terminals
